{"stats":{"minecraft:crafted":{"minecraft:stone_sword":1,"minecraft:oak_planks":16,"minecraft:stick":8,"minecraft:wooden_pickaxe":1,"minecraft:stone_pickaxe":1,"minecraft:furnace":1},"minecraft:used":{"minecraft:iron_chestplate":1,"minecraft:apple":1,"minecraft:bread":2,"minecraft:stone_pickaxe":39,"minecraft:wooden_pickaxe":26},"minecraft:mined":{"minecraft:grass":7,"minecraft:coal_ore":20,"minecraft:oak_log":4,"minecraft:iron_ore":16,"gnumus:fragile_gnumus_jug":2,"farmersdelight:wild_carrots":13,"minecraft:stone":29,"minecraft:oak_leaves":8},"minecraft:picked_up":{"minecraft:raw_iron":16,"minecraft:wheat_seeds":5,"minecraft:raw_gold":1,"minecraft:oak_log":4,"minecraft:carrot":15,"minecraft:gunpowder":1,"minecraft:coal":19,"minecraft:cobblestone":29},"minecraft:custom":{"minecraft:open_barrel":4,"minecraft:time_since_rest":12366,"minecraft:play_time":28137,"minecraft:sprint_one_cm":73393,"minecraft:deaths":1,"minecraft:damage_taken":338,"minecraft:walk_one_cm":16534,"minecraft:sneak_time":27,"minecraft:walk_under_water_one_cm":6629,"minecraft:drop":5,"minecraft:jump":387,"minecraft:time_since_death":8702,"minecraft:walk_on_water_one_cm":6980,"minecraft:total_world_time":28137,"minecraft:swim_one_cm":7199,"minecraft:interact_with_crafting_table":5,"minecraft:fall_one_cm":9463,"minecraft:fly_one_cm":83400},"minecraft:killed_by":{"born_in_chaos_v1:skeleton_thrasher":1},"minecraft:dropped":{"minecraft:knowledge_book":4,"cnc:field_guide":1}},"DataVersion":3465}