{"stats":{"minecraft:picked_up":{"gnumus:gnumus_pouch_2":2,"gnumus:gnumus_horn":1,"gnumus:gnumus_claw":2,"minecraft:knowledge_book":2,"minecraft:dirt":1,"cnc:field_guide":1},"minecraft:mined":{"minecraft:grass_block":1,"minecraft:dark_oak_leaves":4,"minecraft:spruce_leaves":1},"minecraft:custom":{"minecraft:open_chest":1,"minecraft:time_since_rest":21348,"minecraft:play_time":21348,"minecraft:sprint_one_cm":22757,"minecraft:damage_taken":290,"minecraft:walk_one_cm":39305,"minecraft:walk_under_water_one_cm":1381,"minecraft:drop":16,"minecraft:jump":217,"minecraft:leave_game":9,"minecraft:time_since_death":21348,"minecraft:walk_on_water_one_cm":2147,"minecraft:total_world_time":21348,"minecraft:swim_one_cm":1065,"minecraft:fall_one_cm":9693,"minecraft:fly_one_cm":16870},"minecraft:used":{"minecraft:bread":3},"minecraft:dropped":{"minecraft:knowledge_book":14,"cnc:field_guide":2}},"DataVersion":3465}